{"is_source_file": false, "format": "", "description": "", "external_files": [], "external_methods": [], "published": [], "classes": [], "methods": [], "calls": [], "search-terms": [], "state": 2, "file_id": 5, "knowledge_revision": 14, "git_revision": "0930faa20189d540dd2134d7e9454b6c52c75243", "hash": "07aa094d3074ee74c574f09905fe753c", "format-version": 4, "code-base-name": "AdminService", "filename": "AdminService/README.md", "revision_history": [{"14": "0930faa20189d540dd2134d7e9454b6c52c75243"}]}